ZetcodeKotlinJiaochengChuyi/README.md
ZetcodeKotlinJiaochengChuyi/__init__.py
ZetcodeKotlinJiaochengChuyi/__main__.py
ZetcodeKotlinJiaochengChuyi/file.epub
ZetcodeKotlinJiaochengChuyi/index.html
ZetcodeKotlinJiaochengChuyi/css/__init__.py
ZetcodeKotlinJiaochengChuyi/css/annotations.css
ZetcodeKotlinJiaochengChuyi/css/main.css
ZetcodeKotlinJiaochengChuyi/css/normalize.css
ZetcodeKotlinJiaochengChuyi/css/popup.css
ZetcodeKotlinJiaochengChuyi/font/__init__.py
ZetcodeKotlinJiaochengChuyi/font/fontello.eot
ZetcodeKotlinJiaochengChuyi/font/fontello.svg
ZetcodeKotlinJiaochengChuyi/font/fontello.ttf
ZetcodeKotlinJiaochengChuyi/font/fontello.woff
ZetcodeKotlinJiaochengChuyi/img/__init__.py
ZetcodeKotlinJiaochengChuyi/img/annotator-glyph-sprite.png
ZetcodeKotlinJiaochengChuyi/img/annotator-icon-sprite.png
ZetcodeKotlinJiaochengChuyi/img/apple-touch-icon.png
ZetcodeKotlinJiaochengChuyi/img/cancelfullscreen.png
ZetcodeKotlinJiaochengChuyi/img/close.png
ZetcodeKotlinJiaochengChuyi/img/fullscreen.png
ZetcodeKotlinJiaochengChuyi/img/loader.gif
ZetcodeKotlinJiaochengChuyi/img/menu-icon.png
ZetcodeKotlinJiaochengChuyi/img/save.png
ZetcodeKotlinJiaochengChuyi/img/saved.png
ZetcodeKotlinJiaochengChuyi/img/settings-s.png
ZetcodeKotlinJiaochengChuyi/img/settings.png
ZetcodeKotlinJiaochengChuyi/img/star.png
ZetcodeKotlinJiaochengChuyi/js/__init__.py
ZetcodeKotlinJiaochengChuyi/js/epub.js
ZetcodeKotlinJiaochengChuyi/js/epub.min.js
ZetcodeKotlinJiaochengChuyi/js/epub.min.map
ZetcodeKotlinJiaochengChuyi/js/hooks.min.js
ZetcodeKotlinJiaochengChuyi/js/hooks.min.map
ZetcodeKotlinJiaochengChuyi/js/reader.js
ZetcodeKotlinJiaochengChuyi/js/reader.js.map
ZetcodeKotlinJiaochengChuyi/js/reader.min.js
ZetcodeKotlinJiaochengChuyi/js/reader.min.map
ZetcodeKotlinJiaochengChuyi/js/hooks/__init__.py
ZetcodeKotlinJiaochengChuyi/js/hooks/extensions/__init__.py
ZetcodeKotlinJiaochengChuyi/js/hooks/extensions/highlight.js
ZetcodeKotlinJiaochengChuyi/js/libs/__init__.py
zetcode_kotlin_jiaocheng_chuyi-2024.3.5.0.dist-info/METADATA
zetcode_kotlin_jiaocheng_chuyi-2024.3.5.0.dist-info/WHEEL
zetcode_kotlin_jiaocheng_chuyi-2024.3.5.0.dist-info/entry_points.txt
zetcode_kotlin_jiaocheng_chuyi-2024.3.5.0.dist-info/top_level.txt
zetcode_kotlin_jiaocheng_chuyi-2024.3.5.0.dist-info/RECORD
